lilya_simple_jwt/__init__.py
lilya_simple_jwt/backends.py
lilya_simple_jwt/config.py
lilya_simple_jwt/controllers.py
lilya_simple_jwt/exceptions.py
lilya_simple_jwt/py.typed
lilya_simple_jwt/schemas.py
lilya_simple_jwt/token.py
lilya_simple_jwt/urls.py
lilya_simple_jwt/utils.py
lilya_simple_jwt-0.1.1.dist-info/METADATA
lilya_simple_jwt-0.1.1.dist-info/WHEEL
lilya_simple_jwt-0.1.1.dist-info/licenses/LICENSE
lilya_simple_jwt-0.1.1.dist-info/RECORD
